{
  "annotations": {
    "changelogDate": "20250526133754"
  },
  "applications": "*",
  "dto": "mapstruct",
  "fields": [
    {
      "fieldName": "id",
      "fieldType": "Integer",
      "fieldValidateRules": ["required"]
    },
    {
      "fieldName": "categorie",
      "fieldType": "String"
    },
    {
      "fieldName": "etablissementRef",
      "fieldType": "Integer"
    }
  ],
  "name": "CategoriePointDeVente",
  "pagination": "pagination",
  "relationships": [],
  "searchEngine": "no",
  "service": "serviceClass"
}
